oarepo_glitchtip/__init__.py
oarepo_glitchtip/ext.py
oarepo_glitchtip/initialize.py
oarepo_glitchtip-1.1.1.dist-info/LICENSE
oarepo_glitchtip-1.1.1.dist-info/METADATA
oarepo_glitchtip-1.1.1.dist-info/WHEEL
oarepo_glitchtip-1.1.1.dist-info/entry_points.txt
oarepo_glitchtip-1.1.1.dist-info/top_level.txt
oarepo_glitchtip-1.1.1.dist-info/RECORD
