Metadata-Version: 2.1
Name: oarepo-glitchtip
Version: 1.1.1
License-File: LICENSE
Requires-Dist: sentry-sdk[flask]
